hypercoerpa/__init__.py
hypercoerpa/function.py
hypercoerpa-0.2.9.dist-info/licenses/LICENCE
hypercoerpa-0.2.9.dist-info/METADATA
hypercoerpa-0.2.9.dist-info/WHEEL
hypercoerpa-0.2.9.dist-info/top_level.txt
hypercoerpa-0.2.9.dist-info/RECORD
