Metadata-Version: 2.4
Name: HyperCoeRPA
Version: 0.2.9
Summary: Repositorio para a utilização da API de Log do HyperCoe
Author: Joao Buso
Author-email: joao.buso@gmail.com
License: MIT License
Keywords: rpa hypercoe log tria software
License-File: LICENCE
Requires-Dist: requests
Dynamic: author
Dynamic: author-email
Dynamic: description
Dynamic: description-content-type
Dynamic: keywords
Dynamic: license
Dynamic: license-file
Dynamic: requires-dist
Dynamic: summary
